academic_mcp/__init__.py
academic_mcp/__main__.py
academic_mcp/sources/__init__.py
academic_mcp/sources/acm.py
academic_mcp/sources/arxiv.py
academic_mcp/sources/biorxiv.py
academic_mcp/sources/core.py
academic_mcp/sources/crossref.py
academic_mcp/sources/google_scholar.py
academic_mcp/sources/hub.py
academic_mcp/sources/iacr.py
academic_mcp/sources/ieee.py
academic_mcp/sources/jstor.py
academic_mcp/sources/medrxiv.py
academic_mcp/sources/pmc.py
academic_mcp/sources/pubmed.py
academic_mcp/sources/researchgate.py
academic_mcp/sources/sci_hub.py
academic_mcp/sources/sciencedirect.py
academic_mcp/sources/scopus.py
academic_mcp/sources/semantic.py
academic_mcp/sources/springer.py
academic_mcp/sources/wos.py
academic_mcp/types.py
academic_mcp-0.1.7.dist-info/METADATA
academic_mcp-0.1.7.dist-info/WHEEL
academic_mcp-0.1.7.dist-info/entry_points.txt
academic_mcp-0.1.7.dist-info/licenses/LICENSE
academic_mcp-0.1.7.dist-info/RECORD
