Metadata-Version: 2.4
Name: academic-mcp
Version: 0.1.7
Summary: A MCP server for searching and downloading academic papers from multiple sources.
License-Expression: MIT
License-File: LICENSE
Author: Xueyuan Lin
Author-email: linxy59@mail2.sysu.edu.cn
Requires-Python: >=3.10
Classifier: Programming Language :: Python :: 3
Classifier: Programming Language :: Python :: 3.10
Classifier: Programming Language :: Python :: 3.11
Classifier: Programming Language :: Python :: 3.12
Classifier: Programming Language :: Python :: 3.13
Classifier: Programming Language :: Python :: 3.14
Requires-Dist: PyPDF2 (>=3.0.0)
Requires-Dist: beautifulsoup4 (>=4.12.0)
Requires-Dist: fastmcp
Requires-Dist: feedparser
Requires-Dist: httpx[socks] (>=0.28.1)
Requires-Dist: loguru (>=0.7.0)
Requires-Dist: lxml (>=4.9.0)
Requires-Dist: mcp[cli] (>=1.6.0)
Requires-Dist: pydantic (>=2.0.0)
Requires-Dist: requests
Requires-Dist: typer (>=0.12.0)
Requires-Dist: uvicorn (>=0.30.0)
Requires-Dist: xlin (>=0.0.4)
